{
  "": "",
  "News app": "",
  "aboutUs": "",
  "actions": {
    "edit": "",
    "refreshPage": ""
  },
  "ar": "",
  "auth": {
    "authForm": "",
    "enterPassword": "",
    "enterUsername": "",
    "logOut": "",
    "signIn": ""
  },
  "authForm": "",
  "authIncorrect": "",
  "edit": "",
  "enterFirstname": "",
  "enterPassword": "",
  "enterUsername": "",
  "fetchProfileError": "",
  "language": "",
  "leave": "",
  "logOut": "",
  "main": "",
  "menu": "",
  "noComments": "",
  "notFoundPage": "",
  "profile": "",
  "refreshPage": "",
  "signIn": "",
  "tryRefresh": "",
  "unexpectedError": "",
  "yourFeedback": "",
  "Введите username": "",
  "Введите пароль": "",
  "Войти": "",
  "Вы ввели неверный логин или пароль": "",
  "Статьи не найдены": "",
  "Форма авторизации": ""
}
